odoo/addons/fieldservice_account/README.rst
odoo/addons/fieldservice_account/__init__.py
odoo/addons/fieldservice_account/__manifest__.py
odoo/addons/fieldservice_account/i18n/de.po
odoo/addons/fieldservice_account/i18n/es.po
odoo/addons/fieldservice_account/i18n/es_AR.po
odoo/addons/fieldservice_account/i18n/es_CL.po
odoo/addons/fieldservice_account/i18n/fieldservice_account.pot
odoo/addons/fieldservice_account/i18n/fr_FR.po
odoo/addons/fieldservice_account/i18n/it.po
odoo/addons/fieldservice_account/i18n/pt_BR.po
odoo/addons/fieldservice_account/i18n/tr.po
odoo/addons/fieldservice_account/migrations/13.0.1.0.0/pre-migration.py
odoo/addons/fieldservice_account/migrations/13.0.2.0.0/post-migration.py
odoo/addons/fieldservice_account/migrations/13.0.2.0.0/pre-migration.py
odoo/addons/fieldservice_account/models/__init__.py
odoo/addons/fieldservice_account/models/account_move.py
odoo/addons/fieldservice_account/models/account_move_line.py
odoo/addons/fieldservice_account/models/fsm_order.py
odoo/addons/fieldservice_account/readme/CONFIGURE.rst
odoo/addons/fieldservice_account/readme/CONTRIBUTORS.rst
odoo/addons/fieldservice_account/readme/CREDITS.rst
odoo/addons/fieldservice_account/readme/DESCRIPTION.rst
odoo/addons/fieldservice_account/readme/INSTALL.rst
odoo/addons/fieldservice_account/readme/USAGE.rst
odoo/addons/fieldservice_account/security/ir.model.access.csv
odoo/addons/fieldservice_account/static/description/icon.png
odoo/addons/fieldservice_account/static/description/index.html
odoo/addons/fieldservice_account/tests/__init__.py
odoo/addons/fieldservice_account/tests/test_fsm_account.py
odoo/addons/fieldservice_account/views/account_move.xml
odoo/addons/fieldservice_account/views/fsm_order.xml
odoo13_addon_fieldservice_account-13.0.2.1.1.dist-info/METADATA
odoo13_addon_fieldservice_account-13.0.2.1.1.dist-info/WHEEL
odoo13_addon_fieldservice_account-13.0.2.1.1.dist-info/top_level.txt
odoo13_addon_fieldservice_account-13.0.2.1.1.dist-info/RECORD
